README.md
setup.py
daisy/__init__.py
daisy/assets/__init__.py
daisy/assets/basic.yaml
daisy/assets/ease.yaml
daisy/assets/fm.yaml
daisy/assets/item2vec.yaml
daisy/assets/itemknn.yaml
daisy/assets/lightgcn.yaml
daisy/assets/mf.yaml
daisy/assets/mostpop.yaml
daisy/assets/multi-vae.yaml
daisy/assets/neumf.yaml
daisy/assets/nfm.yaml
daisy/assets/ngcf.yaml
daisy/assets/puresvd.yaml
daisy/assets/slim.yaml
daisy/model/AbstractRecommender.py
daisy/model/EASERecommender.py
daisy/model/FMRecommender.py
daisy/model/Item2VecRecommender.py
daisy/model/KNNCFRecommender.py
daisy/model/LightGCNRecommender.py
daisy/model/MFRecommender.py
daisy/model/NFMRecommender.py
daisy/model/NGCFRecommender.py
daisy/model/NeuMFRecommender.py
daisy/model/PopRecommender.py
daisy/model/PureSVDRecommender.py
daisy/model/SLiMRecommender.py
daisy/model/VAECFRecommender.py
daisy/model/__init__.py
daisy/utils/__init__.py
daisy/utils/config.py
daisy/utils/dataset.py
daisy/utils/loader.py
daisy/utils/loss.py
daisy/utils/metrics.py
daisy/utils/parser.py
daisy/utils/sampler.py
daisy/utils/splitter.py
daisy/utils/utils.py
daisyRec.egg-info/PKG-INFO
daisyRec.egg-info/SOURCES.txt
daisyRec.egg-info/dependency_links.txt
daisyRec.egg-info/not-zip-safe
daisyRec.egg-info/requires.txt
daisyRec.egg-info/top_level.txt