Metadata-Version: 2.1
Name: daisyRec
Version: 2.2.0
Summary: An easy-to-use library for recommender systems.
Home-page: https://github.com/AmazingDD/daisyRec
Author: Yu Di
Author-email: di.yu.2021@mitb.smu.edu.sg
License: UNKNOWN
Download-URL: https://github.com/AmazingDD/daisyRec/archive/refs/tags/v2.2.0.tar.gz
Keywords: ranking,recommendation
Platform: UNKNOWN
Classifier: License :: OSI Approved :: MIT License
Provides-Extra: optuna
